[
  {
    "city": "Belize City", 
    "lat": "17.4986", 
    "lng": "-88.1886", 
    "country": "Belize", 
    "iso2": "BZ", 
    "admin_name": "Belize", 
    "capital": "admin", 
    "population": "57169", 
    "population_proper": "57169"
  }, 
  {
    "city": "Orange Walk", 
    "lat": "18.0750", 
    "lng": "-88.5583", 
    "country": "Belize", 
    "iso2": "BZ", 
    "admin_name": "Orange Walk", 
    "capital": "admin", 
    "population": "18000", 
    "population_proper": "18000"
  }, 
  {
    "city": "Belmopan", 
    "lat": "17.2500", 
    "lng": "-88.7675", 
    "country": "Belize", 
    "iso2": "BZ", 
    "admin_name": "Cayo", 
    "capital": "primary", 
    "population": "17222", 
    "population_proper": "17222"
  }, 
  {
    "city": "San Ignacio", 
    "lat": "17.1588", 
    "lng": "-89.0696", 
    "country": "Belize", 
    "iso2": "BZ", 
    "admin_name": "Cayo", 
    "capital": "admin", 
    "population": "16977", 
    "population_proper": "16977"
  }, 
  {
    "city": "San Pedro", 
    "lat": "17.9214", 
    "lng": "-87.9611", 
    "country": "Belize", 
    "iso2": "BZ", 
    "admin_name": "Belize", 
    "capital": "", 
    "population": "11767", 
    "population_proper": "11767"
  }, 
  {
    "city": "Dangriga", 
    "lat": "16.9667", 
    "lng": "-88.2167", 
    "country": "Belize", 
    "iso2": "BZ", 
    "admin_name": "Stann Creek", 
    "capital": "admin", 
    "population": "9096", 
    "population_proper": "9096"
  }, 
  {
    "city": "Corozal", 
    "lat": "18.4000", 
    "lng": "-88.4000", 
    "country": "Belize", 
    "iso2": "BZ", 
    "admin_name": "Corozal", 
    "capital": "admin", 
    "population": "8800", 
    "population_proper": "8800"
  }, 
  {
    "city": "Ladyville", 
    "lat": "17.5567", 
    "lng": "-88.2889", 
    "country": "Belize", 
    "iso2": "BZ", 
    "admin_name": "Belize", 
    "capital": "", 
    "population": "5458", 
    "population_proper": "5458"
  }, 
  {
    "city": "Punta Gorda", 
    "lat": "16.1000", 
    "lng": "-88.8000", 
    "country": "Belize", 
    "iso2": "BZ", 
    "admin_name": "Toledo", 
    "capital": "admin", 
    "population": "5026", 
    "population_proper": "5026"
  }, 
  {
    "city": "Trial Farm", 
    "lat": "18.0833", 
    "lng": "-88.5500", 
    "country": "Belize", 
    "iso2": "BZ", 
    "admin_name": "Orange Walk", 
    "capital": "", 
    "population": "4264", 
    "population_proper": "4264"
  }, 
  {
    "city": "Bullet Tree Falls", 
    "lat": "17.1680", 
    "lng": "-89.1110", 
    "country": "Belize", 
    "iso2": "BZ", 
    "admin_name": "Cayo", 
    "capital": "", 
    "population": "2124", 
    "population_proper": "2124"
  }, 
  {
    "city": "Santa Familia", 
    "lat": "17.1850", 
    "lng": "-89.0740", 
    "country": "Belize", 
    "iso2": "BZ", 
    "admin_name": "Cayo", 
    "capital": "", 
    "population": "1598", 
    "population_proper": "1598"
  }, 
  {
    "city": "Consejo", 
    "lat": "18.4583", 
    "lng": "-88.3000", 
    "country": "Belize", 
    "iso2": "BZ", 
    "admin_name": "Corozal", 
    "capital": "", 
    "population": "", 
    "population_proper": ""
  }, 
  {
    "city": "Maya Beach", 
    "lat": "16.6152", 
    "lng": "-88.3542", 
    "country": "Belize", 
    "iso2": "BZ", 
    "admin_name": "Stann Creek", 
    "capital": "", 
    "population": "", 
    "population_proper": ""
  }, 
  {
    "city": "Camelote", 
    "lat": "17.2472", 
    "lng": "-88.8176", 
    "country": "Belize", 
    "iso2": "BZ", 
    "admin_name": "Cayo", 
    "capital": "", 
    "population": "", 
    "population_proper": ""
  }, 
  {
    "city": "Benque Viejo el Carmen", 
    "lat": "17.0667", 
    "lng": "-89.1333", 
    "country": "Belize", 
    "iso2": "BZ", 
    "admin_name": "Cayo", 
    "capital": "", 
    "population": "", 
    "population_proper": ""
  }, 
  {
    "city": "San Estevan", 
    "lat": "18.1550", 
    "lng": "-88.5106", 
    "country": "Belize", 
    "iso2": "BZ", 
    "admin_name": "Orange Walk", 
    "capital": "", 
    "population": "", 
    "population_proper": ""
  }, 
  {
    "city": "San Pablo", 
    "lat": "18.2097", 
    "lng": "-88.5617", 
    "country": "Belize", 
    "iso2": "BZ", 
    "admin_name": "Orange Walk", 
    "capital": "", 
    "population": "", 
    "population_proper": ""
  }, 
  {
    "city": "Guinea Grass", 
    "lat": "17.9681", 
    "lng": "-88.5956", 
    "country": "Belize", 
    "iso2": "BZ", 
    "admin_name": "Orange Walk", 
    "capital": "", 
    "population": "", 
    "population_proper": ""
  }, 
  {
    "city": "Blue Creek Village", 
    "lat": "16.1988", 
    "lng": "-89.0453", 
    "country": "Belize", 
    "iso2": "BZ", 
    "admin_name": "Toledo", 
    "capital": "", 
    "population": "", 
    "population_proper": ""
  }, 
  {
    "city": "Salt Creek", 
    "lat": "17.6631", 
    "lng": "-88.3288", 
    "country": "Belize", 
    "iso2": "BZ", 
    "admin_name": "Belize", 
    "capital": "", 
    "population": "", 
    "population_proper": ""
  }, 
  {
    "city": "Nago Bank", 
    "lat": "17.8803", 
    "lng": "-88.2913", 
    "country": "Belize", 
    "iso2": "BZ", 
    "admin_name": "Belize", 
    "capital": "", 
    "population": "", 
    "population_proper": ""
  }, 
  {
    "city": "More Force", 
    "lat": "17.8426", 
    "lng": "-88.3690", 
    "country": "Belize", 
    "iso2": "BZ", 
    "admin_name": "Belize", 
    "capital": "", 
    "population": "", 
    "population_proper": ""
  }, 
  {
    "city": "White Hill", 
    "lat": "17.2500", 
    "lng": "-88.4833", 
    "country": "Belize", 
    "iso2": "BZ", 
    "admin_name": "Belize", 
    "capital": "", 
    "population": "", 
    "population_proper": ""
  }, 
  {
    "city": "Isabella", 
    "lat": "17.5833", 
    "lng": "-88.5333", 
    "country": "Belize", 
    "iso2": "BZ", 
    "admin_name": "Belize", 
    "capital": "", 
    "population": "", 
    "population_proper": ""
  }, 
  {
    "city": "Flowers Bank", 
    "lat": "17.6141", 
    "lng": "-88.4929", 
    "country": "Belize", 
    "iso2": "BZ", 
    "admin_name": "Belize", 
    "capital": "", 
    "population": "", 
    "population_proper": ""
  }, 
  {
    "city": "Hattieville", 
    "lat": "17.4478", 
    "lng": "-88.3936", 
    "country": "Belize", 
    "iso2": "BZ", 
    "admin_name": "Belize", 
    "capital": "", 
    "population": "", 
    "population_proper": ""
  }, 
  {
    "city": "Lime Walk", 
    "lat": "17.6309", 
    "lng": "-88.4918", 
    "country": "Belize", 
    "iso2": "BZ", 
    "admin_name": "Belize", 
    "capital": "", 
    "population": "", 
    "population_proper": ""
  }, 
  {
    "city": "Sand Hill", 
    "lat": "17.6404", 
    "lng": "-88.3683", 
    "country": "Belize", 
    "iso2": "BZ", 
    "admin_name": "Belize", 
    "capital": "", 
    "population": "", 
    "population_proper": ""
  }, 
  {
    "city": "Egypt", 
    "lat": "17.4253", 
    "lng": "-88.3914", 
    "country": "Belize", 
    "iso2": "BZ", 
    "admin_name": "Belize", 
    "capital": "", 
    "population": "", 
    "population_proper": ""
  }, 
  {
    "city": "Bermudian Landing", 
    "lat": "17.5578", 
    "lng": "-88.5289", 
    "country": "Belize", 
    "iso2": "BZ", 
    "admin_name": "Belize", 
    "capital": "", 
    "population": "", 
    "population_proper": ""
  }, 
  {
    "city": "Scotland", 
    "lat": "17.5667", 
    "lng": "-88.5167", 
    "country": "Belize", 
    "iso2": "BZ", 
    "admin_name": "Belize", 
    "capital": "", 
    "population": "", 
    "population_proper": ""
  }, 
  {
    "city": "Corozalito", 
    "lat": "17.8390", 
    "lng": "-88.2739", 
    "country": "Belize", 
    "iso2": "BZ", 
    "admin_name": "Belize", 
    "capital": "", 
    "population": "", 
    "population_proper": ""
  }, 
  {
    "city": "Maskall", 
    "lat": "17.8779", 
    "lng": "-88.3117", 
    "country": "Belize", 
    "iso2": "BZ", 
    "admin_name": "Belize", 
    "capital": "", 
    "population": "", 
    "population_proper": ""
  }, 
  {
    "city": "Biscayne", 
    "lat": "17.7170", 
    "lng": "-88.4572", 
    "country": "Belize", 
    "iso2": "BZ", 
    "admin_name": "Belize", 
    "capital": "", 
    "population": "", 
    "population_proper": ""
  }, 
  {
    "city": "Butcher Burns", 
    "lat": "17.4109", 
    "lng": "-88.4453", 
    "country": "Belize", 
    "iso2": "BZ", 
    "admin_name": "Belize", 
    "capital": "", 
    "population": "", 
    "population_proper": ""
  }, 
  {
    "city": "Bakers", 
    "lat": "17.5500", 
    "lng": "-88.3833", 
    "country": "Belize", 
    "iso2": "BZ", 
    "admin_name": "Belize", 
    "capital": "", 
    "population": "", 
    "population_proper": ""
  }, 
  {
    "city": "Cedar Bank", 
    "lat": "17.3858", 
    "lng": "-88.4387", 
    "country": "Belize", 
    "iso2": "BZ", 
    "admin_name": "Belize", 
    "capital": "", 
    "population": "", 
    "population_proper": ""
  }, 
  {
    "city": "Davis Bank", 
    "lat": "17.6446", 
    "lng": "-88.3959", 
    "country": "Belize", 
    "iso2": "BZ", 
    "admin_name": "Belize", 
    "capital": "", 
    "population": "", 
    "population_proper": ""
  }, 
  {
    "city": "Santana", 
    "lat": "17.8032", 
    "lng": "-88.2966", 
    "country": "Belize", 
    "iso2": "BZ", 
    "admin_name": "Belize", 
    "capital": "", 
    "population": "", 
    "population_proper": ""
  }, 
  {
    "city": "Bomba", 
    "lat": "17.8917", 
    "lng": "-88.2762", 
    "country": "Belize", 
    "iso2": "BZ", 
    "admin_name": "Belize", 
    "capital": "", 
    "population": "", 
    "population_proper": ""
  }, 
  {
    "city": "Burrell Boom", 
    "lat": "17.5667", 
    "lng": "-88.4000", 
    "country": "Belize", 
    "iso2": "BZ", 
    "admin_name": "Belize", 
    "capital": "", 
    "population": "", 
    "population_proper": ""
  }, 
  {
    "city": "Lucky Strike", 
    "lat": "17.7792", 
    "lng": "-88.3168", 
    "country": "Belize", 
    "iso2": "BZ", 
    "admin_name": "Belize", 
    "capital": "", 
    "population": "", 
    "population_proper": ""
  }, 
  {
    "city": "Little Bermudian Landing", 
    "lat": "17.5753", 
    "lng": "-88.5419", 
    "country": "Belize", 
    "iso2": "BZ", 
    "admin_name": "Belize", 
    "capital": "", 
    "population": "", 
    "population_proper": ""
  }, 
  {
    "city": "Washing Tree", 
    "lat": "17.6853", 
    "lng": "-88.4604", 
    "country": "Belize", 
    "iso2": "BZ", 
    "admin_name": "Belize", 
    "capital": "", 
    "population": "", 
    "population_proper": ""
  }, 
  {
    "city": "Ferguson Bank", 
    "lat": "17.4419", 
    "lng": "-88.2953", 
    "country": "Belize", 
    "iso2": "BZ", 
    "admin_name": "Belize", 
    "capital": "", 
    "population": "", 
    "population_proper": ""
  }, 
  {
    "city": "Grace Bank", 
    "lat": "17.6498", 
    "lng": "-88.4049", 
    "country": "Belize", 
    "iso2": "BZ", 
    "admin_name": "Belize", 
    "capital": "", 
    "population": "", 
    "population_proper": ""
  }, 
  {
    "city": "Watters Bank", 
    "lat": "17.3120", 
    "lng": "-88.3561", 
    "country": "Belize", 
    "iso2": "BZ", 
    "admin_name": "Belize", 
    "capital": "", 
    "population": "", 
    "population_proper": ""
  }, 
  {
    "city": "Rockstone Pond", 
    "lat": "17.7539", 
    "lng": "-88.3437", 
    "country": "Belize", 
    "iso2": "BZ", 
    "admin_name": "Belize", 
    "capital": "", 
    "population": "", 
    "population_proper": ""
  }, 
  {
    "city": "Caye Corker", 
    "lat": "17.7398", 
    "lng": "-88.0256", 
    "country": "Belize", 
    "iso2": "BZ", 
    "admin_name": "Belize", 
    "capital": "", 
    "population": "", 
    "population_proper": ""
  }, 
  {
    "city": "May Pen", 
    "lat": "17.6554", 
    "lng": "-88.4713", 
    "country": "Belize", 
    "iso2": "BZ", 
    "admin_name": "Belize", 
    "capital": "", 
    "population": "", 
    "population_proper": ""
  }, 
  {
    "city": "Rockville", 
    "lat": "17.4000", 
    "lng": "-88.4667", 
    "country": "Belize", 
    "iso2": "BZ", 
    "admin_name": "Belize", 
    "capital": "", 
    "population": "", 
    "population_proper": ""
  }, 
  {
    "city": "Gales Point", 
    "lat": "17.1710", 
    "lng": "-88.3352", 
    "country": "Belize", 
    "iso2": "BZ", 
    "admin_name": "Belize", 
    "capital": "", 
    "population": "", 
    "population_proper": ""
  }, 
  {
    "city": "Bocotora", 
    "lat": "17.2575", 
    "lng": "-88.4345", 
    "country": "Belize", 
    "iso2": "BZ", 
    "admin_name": "Belize", 
    "capital": "", 
    "population": "", 
    "population_proper": ""
  }, 
  {
    "city": "Tropical Park", 
    "lat": "17.4667", 
    "lng": "-88.3833", 
    "country": "Belize", 
    "iso2": "BZ", 
    "admin_name": "Belize", 
    "capital": "", 
    "population": "", 
    "population_proper": ""
  }, 
  {
    "city": "Cowhead Creek", 
    "lat": "17.7617", 
    "lng": "-88.3126", 
    "country": "Belize", 
    "iso2": "BZ", 
    "admin_name": "Belize", 
    "capital": "", 
    "population": "", 
    "population_proper": ""
  }, 
  {
    "city": "Joe Wagner Boom", 
    "lat": "17.4234", 
    "lng": "-88.3643", 
    "country": "Belize", 
    "iso2": "BZ", 
    "admin_name": "Belize", 
    "capital": "", 
    "population": "", 
    "population_proper": ""
  }, 
  {
    "city": "Freetown Sibun", 
    "lat": "17.4250", 
    "lng": "-88.3540", 
    "country": "Belize", 
    "iso2": "BZ", 
    "admin_name": "Belize", 
    "capital": "", 
    "population": "", 
    "population_proper": ""
  }, 
  {
    "city": "Chicago", 
    "lat": "17.8152", 
    "lng": "-88.3116", 
    "country": "Belize", 
    "iso2": "BZ", 
    "admin_name": "Belize", 
    "capital": "", 
    "population": "", 
    "population_proper": ""
  }, 
  {
    "city": "Gracy Rock Bank", 
    "lat": "17.3658", 
    "lng": "-88.4497", 
    "country": "Belize", 
    "iso2": "BZ", 
    "admin_name": "Belize", 
    "capital": "", 
    "population": "", 
    "population_proper": ""
  }, 
  {
    "city": "Bob Eiley", 
    "lat": "17.7041", 
    "lng": "-88.4856", 
    "country": "Belize", 
    "iso2": "BZ", 
    "admin_name": "Belize", 
    "capital": "", 
    "population": "", 
    "population_proper": ""
  }, 
  {
    "city": "Santiago Jalacte", 
    "lat": "16.2450", 
    "lng": "-89.2020", 
    "country": "Belize", 
    "iso2": "BZ", 
    "admin_name": "Toledo", 
    "capital": "", 
    "population": "", 
    "population_proper": ""
  }, 
  {
    "city": "Rancho", 
    "lat": "17.9594", 
    "lng": "-88.3725", 
    "country": "Belize", 
    "iso2": "BZ", 
    "admin_name": "Orange Walk", 
    "capital": "", 
    "population": "", 
    "population_proper": ""
  }, 
  {
    "city": "Bacalar Chico", 
    "lat": "18.1866", 
    "lng": "-87.8604", 
    "country": "Belize", 
    "iso2": "BZ", 
    "admin_name": "Belize", 
    "capital": "", 
    "population": "", 
    "population_proper": ""
  }, 
  {
    "city": "San Antonio", 
    "lat": "18.4018", 
    "lng": "-88.3998", 
    "country": "Belize", 
    "iso2": "BZ", 
    "admin_name": "Corozal", 
    "capital": "", 
    "population": "", 
    "population_proper": ""
  }, 
  {
    "city": "Estrella", 
    "lat": "18.2911", 
    "lng": "-88.4523", 
    "country": "Belize", 
    "iso2": "BZ", 
    "admin_name": "Corozal", 
    "capital": "", 
    "population": "", 
    "population_proper": ""
  }, 
  {
    "city": "Pueblo Nuevo", 
    "lat": "18.3098", 
    "lng": "-88.4129", 
    "country": "Belize", 
    "iso2": "BZ", 
    "admin_name": "Corozal", 
    "capital": "", 
    "population": "", 
    "population_proper": ""
  }, 
  {
    "city": "Chunch", 
    "lat": "18.3000", 
    "lng": "-88.3833", 
    "country": "Belize", 
    "iso2": "BZ", 
    "admin_name": "Corozal", 
    "capital": "", 
    "population": "", 
    "population_proper": ""
  }, 
  {
    "city": "Carolina", 
    "lat": "18.3655", 
    "lng": "-88.4283", 
    "country": "Belize", 
    "iso2": "BZ", 
    "admin_name": "Corozal", 
    "capital": "", 
    "population": "", 
    "population_proper": ""
  }, 
  {
    "city": "Benque Viejo", 
    "lat": "18.2766", 
    "lng": "-88.4559", 
    "country": "Belize", 
    "iso2": "BZ", 
    "admin_name": "Corozal", 
    "capital": "", 
    "population": "", 
    "population_proper": ""
  }, 
  {
    "city": "Campa Pita", 
    "lat": "18.0783", 
    "lng": "-88.2995", 
    "country": "Belize", 
    "iso2": "BZ", 
    "admin_name": "Corozal", 
    "capital": "", 
    "population": "", 
    "population_proper": ""
  }, 
  {
    "city": "Shipstern", 
    "lat": "18.1862", 
    "lng": "-88.1685", 
    "country": "Belize", 
    "iso2": "BZ", 
    "admin_name": "Corozal", 
    "capital": "", 
    "population": "", 
    "population_proper": ""
  }, 
  {
    "city": "Yo Chen", 
    "lat": "18.3548", 
    "lng": "-88.4977", 
    "country": "Belize", 
    "iso2": "BZ", 
    "admin_name": "Corozal", 
    "capital": "", 
    "population": "", 
    "population_proper": ""
  }, 
  {
    "city": "Cowpen", 
    "lat": "18.2222", 
    "lng": "-88.2266", 
    "country": "Belize", 
    "iso2": "BZ", 
    "admin_name": "Corozal", 
    "capital": "", 
    "population": "", 
    "population_proper": ""
  }, 
  {
    "city": "Cocos", 
    "lat": "18.2514", 
    "lng": "-88.3734", 
    "country": "Belize", 
    "iso2": "BZ", 
    "admin_name": "Corozal", 
    "capital": "", 
    "population": "", 
    "population_proper": ""
  }, 
  {
    "city": "Cristo Rey", 
    "lat": "18.3486", 
    "lng": "-88.4955", 
    "country": "Belize", 
    "iso2": "BZ", 
    "admin_name": "Corozal", 
    "capital": "", 
    "population": "", 
    "population_proper": ""
  }, 
  {
    "city": "Remate", 
    "lat": "18.4531", 
    "lng": "-88.4134", 
    "country": "Belize", 
    "iso2": "BZ", 
    "admin_name": "Corozal", 
    "capital": "", 
    "population": "", 
    "population_proper": ""
  }, 
  {
    "city": "Chan Chen", 
    "lat": "18.4333", 
    "lng": "-88.4167", 
    "country": "Belize", 
    "iso2": "BZ", 
    "admin_name": "Corozal", 
    "capital": "", 
    "population": "", 
    "population_proper": ""
  }, 
  {
    "city": "Tacistal", 
    "lat": "18.3840", 
    "lng": "-88.4427", 
    "country": "Belize", 
    "iso2": "BZ", 
    "admin_name": "Corozal", 
    "capital": "", 
    "population": "", 
    "population_proper": ""
  }, 
  {
    "city": "San Francisco", 
    "lat": "18.3239", 
    "lng": "-88.4582", 
    "country": "Belize", 
    "iso2": "BZ", 
    "admin_name": "Corozal", 
    "capital": "", 
    "population": "", 
    "population_proper": ""
  }, 
  {
    "city": "Puebla Nueva", 
    "lat": "18.3106", 
    "lng": "-88.4123", 
    "country": "Belize", 
    "iso2": "BZ", 
    "admin_name": "Corozal", 
    "capital": "", 
    "population": "", 
    "population_proper": ""
  }, 
  {
    "city": "Santa Rita", 
    "lat": "18.3897", 
    "lng": "-88.3891", 
    "country": "Belize", 
    "iso2": "BZ", 
    "admin_name": "Corozal", 
    "capital": "", 
    "population": "", 
    "population_proper": ""
  }, 
  {
    "city": "San Pedro", 
    "lat": "18.3376", 
    "lng": "-88.4949", 
    "country": "Belize", 
    "iso2": "BZ", 
    "admin_name": "Corozal", 
    "capital": "", 
    "population": "", 
    "population_proper": ""
  }, 
  {
    "city": "Rancho Corozal", 
    "lat": "18.2560", 
    "lng": "-88.4073", 
    "country": "Belize", 
    "iso2": "BZ", 
    "admin_name": "Corozal", 
    "capital": "", 
    "population": "", 
    "population_proper": ""
  }, 
  {
    "city": "Villa Alfonso", 
    "lat": "18.2833", 
    "lng": "-88.4500", 
    "country": "Belize", 
    "iso2": "BZ", 
    "admin_name": "Corozal", 
    "capital": "", 
    "population": "", 
    "population_proper": ""
  }, 
  {
    "city": "Aventura", 
    "lat": "18.3301", 
    "lng": "-88.4488", 
    "country": "Belize", 
    "iso2": "BZ", 
    "admin_name": "Corozal", 
    "capital": "", 
    "population": "", 
    "population_proper": ""
  }, 
  {
    "city": "Chunox", 
    "lat": "18.2978", 
    "lng": "-88.3575", 
    "country": "Belize", 
    "iso2": "BZ", 
    "admin_name": "Corozal", 
    "capital": "", 
    "population": "", 
    "population_proper": ""
  }, 
  {
    "city": "San Joaquin", 
    "lat": "18.3527", 
    "lng": "-88.4420", 
    "country": "Belize", 
    "iso2": "BZ", 
    "admin_name": "Corozal", 
    "capital": "", 
    "population": "", 
    "population_proper": ""
  }, 
  {
    "city": "Patchchacan", 
    "lat": "18.4006", 
    "lng": "-88.4715", 
    "country": "Belize", 
    "iso2": "BZ", 
    "admin_name": "Corozal", 
    "capital": "", 
    "population": "", 
    "population_proper": ""
  }, 
  {
    "city": "Concepcion", 
    "lat": "18.3231", 
    "lng": "-88.4742", 
    "country": "Belize", 
    "iso2": "BZ", 
    "admin_name": "Corozal", 
    "capital": "", 
    "population": "", 
    "population_proper": ""
  }, 
  {
    "city": "Libertad", 
    "lat": "18.3085", 
    "lng": "-88.4557", 
    "country": "Belize", 
    "iso2": "BZ", 
    "admin_name": "Corozal", 
    "capital": "", 
    "population": "", 
    "population_proper": ""
  }, 
  {
    "city": "Chacan Chac Mol", 
    "lat": "18.2738", 
    "lng": "-88.2574", 
    "country": "Belize", 
    "iso2": "BZ", 
    "admin_name": "Corozal", 
    "capital": "", 
    "population": "", 
    "population_proper": ""
  }, 
  {
    "city": "Calcutta", 
    "lat": "18.3618", 
    "lng": "-88.4388", 
    "country": "Belize", 
    "iso2": "BZ", 
    "admin_name": "Corozal", 
    "capital": "", 
    "population": "", 
    "population_proper": ""
  }, 
  {
    "city": "Shipstern Landing", 
    "lat": "18.2333", 
    "lng": "-88.1844", 
    "country": "Belize", 
    "iso2": "BZ", 
    "admin_name": "Corozal", 
    "capital": "", 
    "population": "", 
    "population_proper": ""
  }, 
  {
    "city": "Hill Bank", 
    "lat": "18.2456", 
    "lng": "-88.3945", 
    "country": "Belize", 
    "iso2": "BZ", 
    "admin_name": "Corozal", 
    "capital": "", 
    "population": "", 
    "population_proper": ""
  }, 
  {
    "city": "Louisville", 
    "lat": "18.3195", 
    "lng": "-88.5098", 
    "country": "Belize", 
    "iso2": "BZ", 
    "admin_name": "Corozal", 
    "capital": "", 
    "population": "", 
    "population_proper": ""
  }, 
  {
    "city": "San Andres", 
    "lat": "18.3892", 
    "lng": "-88.4094", 
    "country": "Belize", 
    "iso2": "BZ", 
    "admin_name": "Corozal", 
    "capital": "", 
    "population": "", 
    "population_proper": ""
  }, 
  {
    "city": "Sarteneja", 
    "lat": "18.3500", 
    "lng": "-88.1333", 
    "country": "Belize", 
    "iso2": "BZ", 
    "admin_name": "Corozal", 
    "capital": "", 
    "population": "", 
    "population_proper": ""
  }, 
  {
    "city": "Laguna", 
    "lat": "18.3825", 
    "lng": "-88.5180", 
    "country": "Belize", 
    "iso2": "BZ", 
    "admin_name": "Corozal", 
    "capital": "", 
    "population": "", 
    "population_proper": ""
  }, 
  {
    "city": "San Fernando", 
    "lat": "18.3213", 
    "lng": "-88.3544", 
    "country": "Belize", 
    "iso2": "BZ", 
    "admin_name": "Corozal", 
    "capital": "", 
    "population": "", 
    "population_proper": ""
  }
]